ukrdc_stats/__init__.py
ukrdc_stats/calculators/README.md
ukrdc_stats/calculators/__init__.py
ukrdc_stats/calculators/abc.py
ukrdc_stats/calculators/ckd.py
ukrdc_stats/calculators/demographics.py
ukrdc_stats/calculators/krt.py
ukrdc_stats/descriptions.py
ukrdc_stats/exceptions.py
ukrdc_stats/models/__init__.py
ukrdc_stats/models/base.py
ukrdc_stats/models/generic_2d.py
ukrdc_stats/models/maps.py
ukrdc_stats/models/networks.py
ukrdc_stats/models/reports.py
ukrdc_stats/py.typed
ukrdc_stats/utils.py
ukrdc_stats-2.13.1.dist-info/METADATA
ukrdc_stats-2.13.1.dist-info/WHEEL
ukrdc_stats-2.13.1.dist-info/licenses/LICENSE
ukrdc_stats-2.13.1.dist-info/RECORD
